tikrecording/__init__.py
tikrecording/api.py
tikrecording/converter.py
tikrecording/exceptions.py
tikrecording/recorder.py
tikrecording-1.0.2.dist-info/licenses/License
tikrecording-1.0.2.dist-info/METADATA
tikrecording-1.0.2.dist-info/WHEEL
tikrecording-1.0.2.dist-info/top_level.txt
tikrecording-1.0.2.dist-info/RECORD
