Metadata-Version: 2.4
Name: tikrecording
Version: 1.0.2
Summary: A Python library to record live sessions from TikTok.
Author-email: Chill4Share <chill4share@gmail.com>
License: MIT License
Classifier: Programming Language :: Python :: 3
Classifier: Operating System :: OS Independent
Requires-Python: >=3.8
License-File: License
Requires-Dist: requests>=2.25.0
Requires-Dist: tenacity>=8.0.0
Dynamic: license-file
